distributed_kron/__init__.py
distributed_kron/kron.py
distributed_kron/pro.py
distributed_kron-2.0.0.dist-info/licenses/LICENSE
distributed_kron-2.0.0.dist-info/WHEEL
distributed_kron-2.0.0.dist-info/METADATA
distributed_kron-2.0.0.dist-info/RECORD
