Metadata-Version: 2.4
Name: distributed-kron
Version: 2.0.0
Summary: An implementation of PSGD Kron optimizer in JAX/optax for large scale distributed training.
Keywords: python,machine learning,deep learning,optimization,jax
Author: Evan Walters
Requires-Python: >=3.10
Classifier: Environment :: Console
Classifier: Programming Language :: Python
Classifier: Intended Audience :: Developers
Classifier: Intended Audience :: Science/Research
Classifier: Operating System :: OS Independent
Classifier: Development Status :: 4 - Beta
Classifier: Topic :: Scientific/Engineering
Classifier: Topic :: Scientific/Engineering :: Artificial Intelligence
Classifier: Topic :: Scientific/Engineering :: Mathematics
Classifier: Topic :: Software Development :: Libraries :: Python Modules
License-File: LICENSE
Requires-Dist: numpy
Requires-Dist: chex
Requires-Dist: jax
Requires-Dist: jaxlib
Requires-Dist: optax
Project-URL: documentation, https://github.com/evanatyourservice/distributed_kron#readme
Project-URL: homepage, https://github.com/evanatyourservice/distributed_kron
Project-URL: repository, https://github.com/evanatyourservice/distributed_kron
